{
    "title": "15D/12N The Best of Balkans with Eastern Europe Experience 2026",
    "folder": "",
    "details": "<p>Experience the best of Eastern Europe and the Balkans as you explore Hungary, Bosnia &amp; Herzegovina, Croatia, Montenegro, Slovenia, and Austria. Visit UNESCO World Heritage Sites, Game of Thrones filming locations, historic cities, scenic lakes, and iconic landmarks including Budapest, Plitvice Lakes, Dubrovnik, Medjugorje, Lake Bled, and Vienna.</p>",
    "duration": "15 Days / 12 Nights",
    "low": "$3,388 All-in w/ Air Fare",
    "flyer": "",
    "travel_dates": [
        "APR 01 \u2013 15, 2026 (Holy Week)"
    ],
    "itinerary": [
        {
            "day_title": "Day 1: Departure \u2013 Manila \u2708 Budapest",
            "day_details": "Meet at NAIA Terminal 3 for Emirates Airlines check-in. Enjoy in-flight meals and amenities. Flight: EK335 MNL\u2013DXB 23:55\u201304:45 / EK111 DXB\u2013BUD 10:30\u201314:20."
        },
        {
            "day_title": "Day 2: Arrival \u2013 Budapest, Hungary (Dinner)",
            "day_details": "Arrival in Budapest. Meet your Tour Director and transfer to hotel. Dinner and overnight."
        },
        {
            "day_title": "Day 3: Budapest City Tour (Breakfast/Dinner)",
            "day_details": "Explore Buda and Pest. Visit Buda Castle, Savoy Terrace, Matthias Church, Fisherman\u2019s Bastion, St. Stephen\u2019s Basilica, and enjoy a scenic Danube River Cruise."
        },
        {
            "day_title": "Day 4: Zagreb, Croatia (Breakfast/Dinner)",
            "day_details": "City tour of Zagreb including Dolac Bazaar, St. Mark\u2019s Church, Stone Gate, Ban Josip Jelacic Square, Lotr\u0161\u010dak Tower, and Mirogoj Cemetery."
        },
        {
            "day_title": "Day 5: Plitvice \u2013 Split, Croatia (Breakfast/Dinner)",
            "day_details": "Visit Plitvice Lakes National Park with boat ride. Continue to Split for overnight."
        },
        {
            "day_title": "Day 6: Split \u2013 Trogir \u2013 Split (Breakfast/Dinner)",
            "day_details": "Visit UNESCO-listed Trogir Old Town and Cathedral. Continue Split city tour including Diocletian\u2019s Palace, Peristyle, Jupiter\u2019s Temple, and Cathedral."
        },
        {
            "day_title": "Day 7: Medjugorje, Bosnia & Herzegovina (Breakfast/Dinner)",
            "day_details": "Visit Apparition Hill and St. James Church. Free time for devotion and meditation."
        },
        {
            "day_title": "Day 8: Mostar \u2013 Sarajevo (Breakfast/Dinner)",
            "day_details": "Explore Mostar Old Bridge and Turkish Quarter. Continue to Sarajevo for city tour."
        },
        {
            "day_title": "Day 9: Dubrovnik, Croatia (Breakfast/Dinner)",
            "day_details": "Walking tour of Dubrovnik Old Town. Visit Franciscan Monastery, historic pharmacy, and Game of Thrones filming locations."
        },
        {
            "day_title": "Day 10: Perast \u2013 Kotor \u2013 Budva \u2013 Dubrovnik (Breakfast/Dinner)",
            "day_details": "Visit Bay of Kotor, Kotor Old Town, St. Triphun Cathedral, Budva Old Town and Amphitheater."
        },
        {
            "day_title": "Day 11: Sibenik \u2013 Zadar (Breakfast/Dinner)",
            "day_details": "Visit Sibenik Cathedral and Zadar Sea Organ. Transfer to hotel."
        },
        {
            "day_title": "Day 12: Postojna \u2013 Ljubljana (Breakfast/Dinner)",
            "day_details": "Explore Postojna Cave by electric train. Continue to Ljubljana city tour."
        },
        {
            "day_title": "Day 13: Lake Bled \u2013 Vienna (Breakfast/Dinner)",
            "day_details": "Pletna Boat Ride to Lake Bled island. Visit Church of Assumption. Drive to Vienna."
        },
        {
            "day_title": "Day 14: Vienna City Tour \u2013 Parndorf Outlet (Breakfast)",
            "day_details": "Vienna city tour and shopping at Parndorf Designer Outlet. Transfer to airport."
        },
        {
            "day_title": "Day 15: Vienna \u2708 Manila",
            "day_details": "Flight home via Emirates Airlines. EK126 VIE\u2013DXB 22:40\u201306:15 / EK334 DXB\u2013MNL 09:35\u201322:10. Home sweet home."
        }
    ],
    "inclusions": [
        "Roundtrip economy airfare via Emirates Airlines",
        "7 kg hand-carry baggage",
        "30 kg check-in baggage",
        "12 nights hotel accommodation (local 4-star category, twin sharing)",
        "Daily hotel buffet breakfast",
        "12 dinners",
        "All airport and city transfers",
        "Tours and sightseeing as per itinerary",
        "Entrance fees as indicated",
        "English-speaking licensed tour guide",
        "Filipino tour leader",
        "Tipping for guide and driver",
        "City, hotel, and tourist taxes",
        "Pre-departure orientation",
        "Travel kits"
    ],
    "exclusions": [
        "Schengen visa fees and processing \u20b112,000",
        "Airline tax ($200 subject to change)",
        "Travel insurance",
        "Expenses not mentioned in inclusions"
    ],
    "extra_details": [
        "First downpayment: $300 upon reservation",
        "Second downpayment: $300 after one month",
        "Full payment required 45 days before departure",
        "Downpayments are non-refundable",
        "Single supplement: $900",
        "Child rate (0\u20135 years old): $2,250; 6 years old and above same as adult",
        "Subject to force majeure and government restrictions",
        "Terms and conditions apply"
    ],
    "images": [
        "assets/data/packages/europe/Balkans 2025-26/BALKANS.png",
        "assets/data/packages/europe/Balkans 2025-26/balkans1.png",
        "assets/data/packages/europe/Balkans 2025-26/balkans2.png",
        "assets/data/packages/europe/Balkans 2025-26/balkans3.png",
        "assets/data/packages/europe/Balkans 2025-26/balkans4.png"
    ],
    "flight_details": "Emirates Airlines \u2013 EK335 MNL\u2013DXB 23:55\u201304:45 / EK111 DXB\u2013BUD 10:30\u201314:20 / EK126 VIE\u2013DXB 22:40\u201306:15 / EK334 DXB\u2013MNL 09:35\u201322:10",
    "contact": "",
    "flyers": [
        "assets/data/packages/europe/15D 14N Balkans 2025\u201326 with Eastern Europe/Flyer_1769577619.png",
        "assets/data/packages/europe/15D 14N Balkans 2025\u201326 with Eastern Europe/Flyer_1769577608.png"
    ],
    "region": "europe"
}